orcidfetch/__init__.py
orcidfetch/oricd.py
orcidfetch-0.6.dist-info/METADATA
orcidfetch-0.6.dist-info/WHEEL
orcidfetch-0.6.dist-info/top_level.txt
orcidfetch-0.6.dist-info/RECORD
