Metadata-Version: 2.1
Name: orcidfetch
Version: 0.6
Summary: The Orcid class takes an author's name, DOI (Digital Object Identifier), and affiliation to attempt to find the author's ORCID ID. It employs a multi-step process, using external APIs like Orcid API, OpenAlex and CrossRef, to provide a confidence score and the method used to identify the author's ORCID.
Author: Juan Camilo Lopez
Requires-Dist: requests
Requires-Dist: pyalex
Requires-Dist: crossrefapi
Requires-Dist: Unidecode
Requires-Dist: python-dotenv
